envshield/__init__.py
envshield/__main__.py
envshield/cli.py
envshield/state.py
envshield/config/__init.py
envshield/config/manager.py
envshield/core/__init__.py
envshield/core/doctor.py
envshield/core/exceptions.py
envshield/core/file_updater.py
envshield/core/inspector.py
envshield/core/scanner.py
envshield/core/schema_manager.py
envshield/core/setup_manager.py
envshield/parsers/__init__.py
envshield/parsers/_base.py
envshield/parsers/_dotenv.py
envshield/parsers/_python.py
envshield/parsers/factory.py
envshield/tests/__init__.py
envshield/tests/test_cli.py
envshield/tests/core/__init__.py
envshield/tests/core/test_doctor.py
envshield/tests/core/test_scanner_compliance.py
envshield/tests/core/test_schema_manager.py
envshield/tests/core/test_setup_manager.py
envshield/tests/parsers/__init__.py
envshield/tests/parsers/python_parser.py
envshield/tests/parsers/test_dotenv_parser.py
envshield/utils/__init__.py
envshield/utils/git_utils.py
envshield-2.1.0.dist-info/licenses/LICENSE.md
envshield-2.1.0.dist-info/METADATA
envshield-2.1.0.dist-info/WHEEL
envshield-2.1.0.dist-info/entry_points.txt
envshield-2.1.0.dist-info/top_level.txt
envshield-2.1.0.dist-info/RECORD
