Metadata-Version: 2.4
Name: envshield
Version: 2.1.0
Summary: EnvShield: A CLI for secure local environment management and secret prevention.
Author-email: Rabbil Yasar Sajal <rabbilyasar@gmail.com>
License: MIT License
Keywords: environment,security,secrets,cli,devops
Classifier: Development Status :: 4 - Beta
Classifier: Environment :: Console
Classifier: Intended Audience :: Developers
Classifier: License :: OSI Approved :: MIT License
Classifier: Natural Language :: English
Classifier: Operating System :: OS Independent
Classifier: Programming Language :: Python :: 3
Classifier: Programming Language :: Python :: 3.8
Classifier: Programming Language :: Python :: 3.9
Classifier: Programming Language :: Python :: 3.10
Classifier: Programming Language :: Python :: 3.11
Classifier: Programming Language :: Python :: 3.12
Classifier: Topic :: Security
Classifier: Topic :: Software Development :: Build Tools
Classifier: Topic :: Utilities
Requires-Python: >=3.10
License-File: LICENSE.md
Requires-Dist: PyYAML<7.0,>=6.0
Requires-Dist: rich<15.0,>=13.0
Requires-Dist: questionary<3.0,>=2.0
Requires-Dist: typer[all]<1.0,>=0.9
Requires-Dist: toml<1.0,>=0.10
Provides-Extra: dev
Requires-Dist: ruff; extra == "dev"
Requires-Dist: pytest; extra == "dev"
Requires-Dist: pytest-mock; extra == "dev"
Requires-Dist: bump2version; extra == "dev"
Dynamic: license-file
